eloquasdk/__init__.py
eloquasdk/bulk.py
eloquasdk/error.py
eloquasdk/login.py
eloquasdk/rest.py
eloquasdk/utils.py
eloqua_python_sdk-0.4.9.dist-info/METADATA
eloqua_python_sdk-0.4.9.dist-info/WHEEL
eloqua_python_sdk-0.4.9.dist-info/top_level.txt
eloqua_python_sdk-0.4.9.dist-info/RECORD
