Metadata-Version: 2.1
Name: eloqua-python-sdk
Version: 0.4.9
Summary: Eloqua Python SDK
Home-page: UNKNOWN
Author: Ignotas Petrulis
Author-email: ignotas.petrulis@gmail.com
License: UNKNOWN
Platform: UNKNOWN
Requires-Dist: requests
Requires-Dist: requests-oauthlib
